{
  "_description": "High quality training configuration - for best performance",
  "_use_case": "Production models, research, final training runs",
  "_hardware": "High-end hardware recommended (32+ GB RAM, RTX 4090 or similar)",
  
  "data": "training_data.txt",
  "output": "nnue_model_hq.bin",
  
  "epochs": 500,
  "batch-size": 16384,
  "lr": 0.0015,
  "lr-scheduler": "adaptive",
  "lr-auto-scale": true,
  
  "feature-size": 115,
  "hidden-size": 768,
  "val-split": 0.08,
  
  "device": "auto",
  
  "plot": true,
  "plot-dir": "plots_hq",
  "plot-interval": 10,
  "save-csv": true,
  "show-plots": false
}
